object_storage/__init__.py
object_storage/object_storage.py
nnsay_object_storage-1.0.2.dist-info/METADATA
nnsay_object_storage-1.0.2.dist-info/WHEEL
nnsay_object_storage-1.0.2.dist-info/RECORD
