Metadata-Version: 2.1
Name: nnsay.object-storage
Version: 1.0.2
Summary: Automatically generated by Nx.
License: Proprietary
Author: Jimmy Wang
Author-email: jimmy.w@aliyun.com
Requires-Python: >=3.9
Classifier: License :: Other/Proprietary License
Classifier: Programming Language :: Python :: 3
Classifier: Programming Language :: Python :: 3.9
Classifier: Programming Language :: Python :: 3.10
Classifier: Programming Language :: Python :: 3.11
Classifier: Programming Language :: Python :: 3.12
Requires-Dist: boto3 (>=1.34.65,<2.0.0)
